{
  "total_count": 1,
  "jobs": [
    {
      "id": 40775118634,
      "run_id": 14532632543,
      "workflow_name": "Sync GitHub Insights (Fixed)",
      "head_branch": "main",
      "run_url": "https://api.github.com/repos/mrkurger/date-night-app2/actions/runs/14532632543",
      "run_attempt": 1,
      "node_id": "CR_kwDOOTqpm88AAAAJfmLvKg",
      "head_sha": "326a8ad4dacd936ca692e618563dd59f6cb5e286",
      "url": "https://api.github.com/repos/mrkurger/date-night-app2/actions/jobs/40775118634",
      "html_url": "https://github.com/mrkurger/date-night-app2/actions/runs/14532632543/job/40775118634",
      "status": "completed",
      "conclusion": "failure",
      "created_at": "2025-04-18T08:56:42Z",
      "started_at": "2025-04-18T08:56:44Z",
      "completed_at": "2025-04-18T08:56:59Z",
      "name": "sync-insights",
      "steps": [
        {
          "name": "Set up job",
          "status": "completed",
          "conclusion": "success",
          "number": 1,
          "started_at": "2025-04-18T08:56:45Z",
          "completed_at": "2025-04-18T08:56:47Z"
        },
        {
          "name": "Run actions/checkout@v4",
          "status": "completed",
          "conclusion": "success",
          "number": 2,
          "started_at": "2025-04-18T08:56:47Z",
          "completed_at": "2025-04-18T08:56:50Z"
        },
        {
          "name": "Set up Node.js",
          "status": "completed",
          "conclusion": "success",
          "number": 3,
          "started_at": "2025-04-18T08:56:50Z",
          "completed_at": "2025-04-18T08:56:53Z"
        },
        {
          "name": "Install dependencies",
          "status": "completed",
          "conclusion": "failure",
          "number": 4,
          "started_at": "2025-04-18T08:56:53Z",
          "completed_at": "2025-04-18T08:56:57Z"
        },
        {
          "name": "Generate GitHub Insights Report",
          "status": "completed",
          "conclusion": "skipped",
          "number": 5,
          "started_at": "2025-04-18T08:56:57Z",
          "completed_at": "2025-04-18T08:56:57Z"
        },
        {
          "name": "Commit Report",
          "status": "completed",
          "conclusion": "skipped",
          "number": 6,
          "started_at": "2025-04-18T08:56:57Z",
          "completed_at": "2025-04-18T08:56:57Z"
        },
        {
          "name": "Post Set up Node.js",
          "status": "completed",
          "conclusion": "skipped",
          "number": 11,
          "started_at": "2025-04-18T08:56:57Z",
          "completed_at": "2025-04-18T08:56:57Z"
        },
        {
          "name": "Post Run actions/checkout@v4",
          "status": "completed",
          "conclusion": "success",
          "number": 12,
          "started_at": "2025-04-18T08:56:57Z",
          "completed_at": "2025-04-18T08:56:57Z"
        },
        {
          "name": "Complete job",
          "status": "completed",
          "conclusion": "success",
          "number": 13,
          "started_at": "2025-04-18T08:56:57Z",
          "completed_at": "2025-04-18T08:56:57Z"
        }
      ],
      "check_run_url": "https://api.github.com/repos/mrkurger/date-night-app2/check-runs/40775118634",
      "labels": [
        "ubuntu-latest"
      ],
      "runner_id": 1000000329,
      "runner_name": "GitHub Actions",
      "runner_group_id": 0,
      "runner_group_name": ""
    }
  ]
}
